target_bigquery/__init__.py
target_bigquery/db_sync.py
target_bigquery/exceptions.py
target_bigquery/flattening.py
target_bigquery/sql_utils.py
target_bigquery/stream_ref_helper.py
target_bigquery/stream_utils.py
pipelinewise_target_bigquery-1.5.0.dist-info/LICENSE
pipelinewise_target_bigquery-1.5.0.dist-info/METADATA
pipelinewise_target_bigquery-1.5.0.dist-info/WHEEL
pipelinewise_target_bigquery-1.5.0.dist-info/entry_points.txt
pipelinewise_target_bigquery-1.5.0.dist-info/top_level.txt
pipelinewise_target_bigquery-1.5.0.dist-info/RECORD
