Metadata-Version: 2.1
Name: pipelinewise-target-bigquery
Version: 1.5.0
Summary: Singer.io target for loading data to BigQuery - PipelineWise compatible
Home-page: https://github.com/transferwise/pipelinewise-target-bigquery
Author: jmriego
Classifier: License :: OSI Approved :: Apache Software License
Classifier: Programming Language :: Python :: 3 :: Only
License-File: LICENSE
Requires-Dist: pipelinewise-singer-python (<3,>=1)
Requires-Dist: google-cloud-bigquery (<3.1.0,>=2.20.0)
Requires-Dist: fastavro (<1.4.11,>=0.22.8)
Provides-Extra: test
Requires-Dist: pytest (==7.0.1) ; extra == 'test'
Requires-Dist: pylint (==2.13.4) ; extra == 'test'
Requires-Dist: pytest-cov (==3.0.0) ; extra == 'test'
